queue_tweets/__init__.py
queue_tweets/abstract.py
queue_tweets/exception_handlers.py
queue_tweets/parallel_stream.py
queue_tweets/queue_stream.py
queue_tweets/stream_queue_listener.py
queue_tweets/test/__init__.py
queue_tweets/test/test_queue_stream.py
queue_tweets/test/test_stream_queue_listener.py
queue_tweets-1.0.1.dist-info/METADATA
queue_tweets-1.0.1.dist-info/RECORD
queue_tweets-1.0.1.dist-info/WHEEL
queue_tweets-1.0.1.dist-info/top_level.txt
